CHANGES.rst
MANIFEST.in
Makefile
README.rst
bootstrap.py
buildout.cfg
screenshot1.png
screenshot10.png
screenshot2.png
screenshot3.png
screenshot4.png
screenshot5.png
screenshot6.png
screenshot7.png
screenshot8.png
screenshot9.png
setup.py
collective/__init__.py
collective.pece.egg-info/PKG-INFO
collective.pece.egg-info/SOURCES.txt
collective.pece.egg-info/dependency_links.txt
collective.pece.egg-info/entry_points.txt
collective.pece.egg-info/namespace_packages.txt
collective.pece.egg-info/requires.txt
collective.pece.egg-info/top_level.txt
collective.pece.egg-info/zip-safe
collective/pece/__init__.py
collective/pece/configure.zcml
collective/pece/tests.py
collective/pece/browser/__init__.py
collective/pece/browser/configure.zcml
collective/pece/browser/zotero_view.pt
collective/pece/browser/zotero_view.py
collective/pece/content/__init__.py
collective/pece/content/annotation_view.pt
collective/pece/content/artifact_view.pt
collective/pece/content/artifact_view.py
collective/pece/content/asthma_annotation.py
collective/pece/content/asthma_question.py
collective/pece/content/asthma_response.py
collective/pece/content/audio_artifact.py
collective/pece/content/configure.zcml
collective/pece/content/document_artifact.py
collective/pece/content/image_artifact.py
collective/pece/content/video_artifact.py
collective/pece/profiles/default/metadata.xml
collective/pece/profiles/default/registry.xml
collective/pece/profiles/default/types.xml
collective/pece/profiles/default/types/asthma_annotation.xml
collective/pece/profiles/default/types/asthma_file.xml
collective/pece/profiles/default/types/asthma_question.xml
collective/pece/profiles/default/types/asthma_response.xml
collective/pece/profiles/default/types/audio_artifact.xml
collective/pece/profiles/default/types/collective.cover.content.xml
collective/pece/profiles/default/types/document_artifact.xml
collective/pece/profiles/default/types/image_artifact.xml
collective/pece/profiles/default/types/video_artifact.xml