Metadata-Version: 1.1
Name: collective.pece
Version: 0.0.7
Summary: The Platform for Experimental Collaborative Ethnography (PECE)
Home-page: https://github.com/collective/collective.pece
Author: Alex Clark
Author-email: aclark@aclark.net
License: GPL
Keywords: Plone
Platform: UNKNOWN
Classifier: Framework :: Plone :: 4.3
Classifier: Programming Language :: Python :: 2.7
